{"_type":"export","__export_format":4,"__export_date":"2022-10-24T17:43:05.768Z","__export_source":"insomnia.desktop.app:v2022.5.1","resources":[{"_id":"req_6a74a39a59fe41f69e3bacc45c707066","parentId":"wrk_eee4ebb2260a4b9eb2612a663d5ee1da","modified":1666633160132,"created":1666419503421,"url":"localhost:3000/file/upload","name":"Upload","description":"","method":"POST","body":{"mimeType":"multipart/form-data","params":[{"id":"pair_aa45b11784ad458a8205e0117d99dcf2","name":"file1","value":"","description":"","type":"file","fileName":"/Users/thiago/Desktop/neoway_file_example.txt"}]},"parameters":[],"headers":[{"name":"Content-Type","value":"multipart/form-data","id":"pair_62d94eb5fcb3456a800e3c39fed3bab6"}],"authentication":{},"metaSortKey":-1666419503421,"isPrivate":false,"settingStoreCookies":true,"settingSendCookies":true,"settingDisableRenderRequestBody":false,"settingEncodeUrl":true,"settingRebuildPath":true,"settingFollowRedirects":"global","_type":"request"},{"_id":"wrk_eee4ebb2260a4b9eb2612a663d5ee1da","parentId":null,"modified":1666633208662,"created":1666419491822,"name":"File","description":"","scope":"collection","_type":"workspace"},{"_id":"env_5ef9dcb10b0676c463be2b978d19abb816b784de","parentId":"wrk_eee4ebb2260a4b9eb2612a663d5ee1da","modified":1666419491827,"created":1666419491827,"name":"Base Environment","data":{},"dataPropertyOrder":null,"color":null,"isPrivate":false,"metaSortKey":1666419491827,"_type":"environment"},{"_id":"jar_5ef9dcb10b0676c463be2b978d19abb816b784de","parentId":"wrk_eee4ebb2260a4b9eb2612a663d5ee1da","modified":1666419491828,"created":1666419491828,"name":"Default Jar","cookies":[],"_type":"cookie_jar"},{"_id":"spc_8bdb3457708b473db8f69bebab91f168","parentId":"wrk_eee4ebb2260a4b9eb2612a663d5ee1da","modified":1666419491823,"created":1666419491823,"fileName":"File","contents":"","contentType":"yaml","_type":"api_spec"}]}